cli.py
apollo/__init__.py
apollo/client.py
apollo/const.py
apollo/exceptions.py
apollo/manager.py
apollo/resource.py
apollo/connectors/__init__.py
apollo/connectors/aws/__init__.py
apollo/connectors/google/__init__.py
apollo/connectors/google/base.py
apollo/connectors/google/cloud.py
apollo/connectors/google/local.py
apollo/connectors/microsoft/__init__.py
apollo/connectors/openai/__init__.py
apollo/connectors/openai/base.py
apollo/connectors/openai/cloud.py
apollo/connectors/openai/local.py
apollo/connectors/sightengine/__init__.py
apollo/connectors/sightengine/base.py
apollo/connectors/sightengine/cloud.py
apollo/connectors/sightengine/local.py
apollo/connectors/spot/__init__.py
apollo/database/__init__.py
apollo/database/firebase/__init__.py
apollo/database/firebase/base.py
apollo/database/firebase/cloud.py
apollo/database/firebase/local.py
apollo/database/mongo/__init__.py
apollo/database/mysql/__init__.py
apollo/database/postgres/__init__.py
apollo/database/supabase/__init__.py
apollo/database/supabase/base.py
apollo/database/supabase/cloud.py
apollo/database/supabase/local.py
apollo/plugins/__init__.py
apollo/plugins/utils.py
apollo/plugins/validation.py
apollo/service/__init__.py
apollo/service/graphql/__init__.py
apollo/service/json/__init__.py
apollo/service/json/base.py
apollo/service/json/cloud.py
apollo/service/json/local.py
apollo/tests/__init__.py
apollo_sdk-0.2.11.dist-info/LICENSE
apollo_sdk-0.2.11.dist-info/METADATA
apollo_sdk-0.2.11.dist-info/WHEEL
apollo_sdk-0.2.11.dist-info/entry_points.txt
apollo_sdk-0.2.11.dist-info/top_level.txt
apollo_sdk-0.2.11.dist-info/RECORD
