Metadata-Version: 2.1
Name: apollo-sdk
Version: 0.2.11
Summary: A radically simple framework for ML/AI model management
Home-page: https://github.com/apolloapi/apolloapi
Author: Apollo API
Author-email: adrbrownx@gmail.com
License: Apache License, Version 2.0
Platform: Any
Classifier: Operating System :: OS Independent
Classifier: Programming Language :: Python :: 3
License-File: LICENSE
Requires-Dist: aiohttp (==3.8.4)
Requires-Dist: aiosignal (==1.3.1)
Requires-Dist: altgraph (==0.17.3)
Requires-Dist: asgiref (==3.6.0)
Requires-Dist: async-timeout (==4.0.2)
Requires-Dist: attrs (==22.1.0)
Requires-Dist: bcbio-gff (==0.7.0)
Requires-Dist: biopython (==1.81)
Requires-Dist: CacheControl (==0.12.11)
Requires-Dist: cachetools (==3.1.1)
Requires-Dist: certifi (==2022.12.7)
Requires-Dist: cffi (==1.15.1)
Requires-Dist: cfgv (==3.3.1)
Requires-Dist: charset-normalizer (==2.1.1)
Requires-Dist: click (==8.1.3)
Requires-Dist: cryptography (==40.0.1)
Requires-Dist: decorator (==5.1.1)
Requires-Dist: distlib (==0.3.6)
Requires-Dist: Django (==4.0)
Requires-Dist: django-cors-headers (==3.13.0)
Requires-Dist: django-environ (==0.4.5)
Requires-Dist: django-storages (==1.13.1)
Requires-Dist: djangorestframework (==3.13.1)
Requires-Dist: exceptiongroup (==1.0.4)
Requires-Dist: execnet (==1.9.0)
Requires-Dist: filelock (==3.8.0)
Requires-Dist: firebase-admin (==6.1.0)
Requires-Dist: frozenlist (==1.3.3)
Requires-Dist: gcloud (==0.18.3)
Requires-Dist: google-api-core (==2.11.0)
Requires-Dist: google-api-python-client (==2.87.0)
Requires-Dist: google-auth (==2.19.0)
Requires-Dist: google-auth-httplib2 (==0.1.0)
Requires-Dist: google-cloud-core (==2.3.2)
Requires-Dist: google-cloud-firestore (==2.11.1)
Requires-Dist: google-cloud-storage (==2.9.0)
Requires-Dist: google-crc32c (==1.5.0)
Requires-Dist: google-resumable-media (==2.5.0)
Requires-Dist: googleapis-common-protos (==1.59.0)
Requires-Dist: grpcio (==1.53.0)
Requires-Dist: grpcio-status (==1.53.0)
Requires-Dist: gunicorn (==20.1.0)
Requires-Dist: httplib2 (==0.21.0)
Requires-Dist: identify (==2.5.22)
Requires-Dist: idna (==3.4)
Requires-Dist: iniconfig (==1.1.1)
Requires-Dist: Jinja2 (==3.1.2)
Requires-Dist: libcst (==0.4.9)
Requires-Dist: macholib (==1.16.2)
Requires-Dist: MarkupSafe (==2.1.2)
Requires-Dist: model-bakery (==1.9.0)
Requires-Dist: msgpack (==1.0.5)
Requires-Dist: multidict (==6.0.4)
Requires-Dist: mypy-extensions (==0.4.3)
Requires-Dist: nodeenv (==1.7.0)
Requires-Dist: numpy (==1.24.3)
Requires-Dist: oauth2client (==4.1.3)
Requires-Dist: openai (==0.27.7)
Requires-Dist: packaging (==22.0)
Requires-Dist: platformdirs (==3.2.0)
Requires-Dist: pluggy (==1.0.0)
Requires-Dist: pre-commit (==2.20.0)
Requires-Dist: proto-plus (==1.22.2)
Requires-Dist: protobuf (==4.22.3)
Requires-Dist: psycopg (==3.1.6)
Requires-Dist: psycopg-binary (==3.1.6)
Requires-Dist: psycopg-pool (==3.1.7)
Requires-Dist: psycopg2 (==2.9.3)
Requires-Dist: py (==1.11.0)
Requires-Dist: pyasn1 (==0.4.8)
Requires-Dist: pyasn1-modules (==0.2.8)
Requires-Dist: pycparser (==2.21)
Requires-Dist: pyinstaller (==5.11.0)
Requires-Dist: pyinstaller-hooks-contrib (==2023.3)
Requires-Dist: PyJWT (==2.6.0)
Requires-Dist: pyparsing (==3.0.9)
Requires-Dist: python-dotenv (==1.0.0)
Requires-Dist: pytz (==2022.6)
Requires-Dist: PyYAML (==6.0)
Requires-Dist: requests (==2.28.1)
Requires-Dist: rsa (==4.9)
Requires-Dist: six (==1.16.0)
Requires-Dist: sqlparse (==0.4.3)
Requires-Dist: tabulate (==0.9.0)
Requires-Dist: termcolor (==2.3.0)
Requires-Dist: toml (==0.10.2)
Requires-Dist: tomli (==2.0.0)
Requires-Dist: tqdm (==4.65.0)
Requires-Dist: typing-inspect (==0.8.0)
Requires-Dist: typing-extensions (==4.4.0)
Requires-Dist: tzdata (==2022.7)
Requires-Dist: uritemplate (==4.1.1)
Requires-Dist: urllib3 (==1.26.13)
Requires-Dist: virtualenv (==20.21.0)
Requires-Dist: wait-for-it (==2.2.1)
Requires-Dist: whitenoise (==6.2.0)
Requires-Dist: wrapt (==1.15.0)
Requires-Dist: yarl (==1.9.2)
